pyPasswordValidator
